jageocoder_converter/__init__.py
jageocoder_converter/__main__.py
jageocoder_converter/base_converter.py
jageocoder_converter/base_registry.py
jageocoder_converter/chiban_converter.py
jageocoder_converter/city_converter.py
jageocoder_converter/config.py
jageocoder_converter/data/azacode.jsonl
jageocoder_converter/data/geoshape-pref-geolod-2021.csv
jageocoder_converter/data_manager.py
jageocoder_converter/gaiku_converter.py
jageocoder_converter/geolonia_converter.py
jageocoder_converter/jusho_converter.py
jageocoder_converter/oaza_converter.py
jageocoder_converter/postcoder.py
jageocoder_converter-2.0.3.dist-info/LICENSE
jageocoder_converter-2.0.3.dist-info/METADATA
jageocoder_converter-2.0.3.dist-info/WHEEL
jageocoder_converter-2.0.3.dist-info/RECORD
