Metadata-Version: 2.1
Name: jageocoder-converter
Version: 2.0.3
Summary: Dictionary generator for jageocoder.
Author: "Takeshi Sagara"
Author-email: sagara@info-proto.com
Requires-Python: >=3.8.1,<4.0.0
Classifier: Programming Language :: Python :: 3
Classifier: Programming Language :: Python :: 3.9
Classifier: Programming Language :: Python :: 3.10
Classifier: Programming Language :: Python :: 3.11
Requires-Dist: certifi (>=2023.7.22)
Requires-Dist: docopt (>=0.6.2,<0.7.0)
Requires-Dist: jaconv (>=0.3.4,<0.4.0)
Requires-Dist: jageocoder (==2.1.0)
Requires-Dist: pycapnp (>=1.3.0,<2.0.0)
Requires-Dist: pyproj (>=3.4.1,<4.0.0)
